python_topsis_Samridhi_101916086/__init__.py
python_topsis_Samridhi_101916086/topsis.py
python_topsis_Samridhi_101916086-4.3.1.dist-info/LICENSE
python_topsis_Samridhi_101916086-4.3.1.dist-info/METADATA
python_topsis_Samridhi_101916086-4.3.1.dist-info/WHEEL
python_topsis_Samridhi_101916086-4.3.1.dist-info/top_level.txt
python_topsis_Samridhi_101916086-4.3.1.dist-info/RECORD
