Metadata-Version: 2.1
Name: python-topsis-Samridhi-101916086
Version: 4.3.1
Summary: Topsis score and rank generator
Home-page: https://github.com/Samridhi412/python_topsis_Samridhi_101916086
Author: Samridhi
Author-email: sgarg7_be19@thapar.edu
License: UNKNOWN
Platform: UNKNOWN
Classifier: Programming Language :: Python :: 3
Classifier: License :: OSI Approved :: MIT License
Classifier: Operating System :: OS Independent
License-File: LICENSE
